{
  "counts": {
    "items": 1115,
    "shaped": 733,
    "shapeless": 323,
    "special": 31,
    "texturesCopied": 766,
    "transmute": 33
  },
  "unresolvedIcons": [
    "black_banner",
    "black_shulker_box",
    "blue_banner",
    "blue_shulker_box",
    "brown_banner",
    "brown_shulker_box",
    "chest",
    "conduit",
    "copper_chest",
    "copper_golem_statue",
    "creeper_head",
    "cyan_banner",
    "cyan_shulker_box",
    "decorated_pot",
    "ender_chest",
    "exposed_copper_chest",
    "exposed_copper_golem_statue",
    "gray_banner",
    "gray_shulker_box",
    "green_banner",
    "green_shulker_box",
    "light_blue_banner",
    "light_blue_shulker_box",
    "light_gray_banner",
    "light_gray_shulker_box",
    "lime_banner",
    "lime_shulker_box",
    "magenta_banner",
    "magenta_shulker_box",
    "orange_banner",
    "orange_shulker_box",
    "oxidized_copper_chest",
    "oxidized_copper_golem_statue",
    "pink_banner",
    "pink_shulker_box",
    "purple_banner",
    "purple_shulker_box",
    "red_banner",
    "red_shulker_box",
    "shield",
    "shulker_box",
    "trapped_chest",
    "waxed_copper_chest",
    "waxed_copper_golem_statue",
    "waxed_exposed_copper_chest",
    "waxed_exposed_copper_golem_statue",
    "waxed_oxidized_copper_chest",
    "waxed_oxidized_copper_golem_statue",
    "waxed_weathered_copper_chest",
    "waxed_weathered_copper_golem_statue",
    "weathered_copper_chest",
    "weathered_copper_golem_statue",
    "white_banner",
    "white_shulker_box",
    "wither_skeleton_skull",
    "yellow_banner",
    "yellow_shulker_box"
  ],
  "version": "26.2"
}
